userenv/__init__.py
userenv-0.0.0.dist-info/METADATA
userenv-0.0.0.dist-info/WHEEL
userenv-0.0.0.dist-info/licenses/LICENSE.txt
userenv-0.0.0.dist-info/RECORD
