Metadata-Version: 2.3
Name: userenv
Version: 0.0.0
Summary: User environment utility
Author-email: Furechan <furechan@xsmail.com>
License-File: LICENSE.txt
Keywords: utility
Classifier: Development Status :: 1 - Planning
Classifier: License :: OSI Approved :: MIT License
Classifier: Operating System :: OS Independent
Classifier: Programming Language :: Python :: 3
Requires-Python: >=3.7
